CHANGELOG.rst
ChangeLog.rst
INSTALL.rst
MANIFEST.in
README.rst
USAGE.rst
coveragerc
setup.py
doc/api.rst
doc/conf.py
doc/globs.rst
doc/index.rst
doc/installation.rst
doc/usage.rst
doc/_static/default.css
formic/LICENSE.txt
formic/VERSION.txt
formic/__init__.py
formic/command.py
formic/formic.py
formic/test_formic.py
formic.egg-info/.DS_Store
formic.egg-info/PKG-INFO
formic.egg-info/SOURCES.txt
formic.egg-info/dependency_links.txt
formic.egg-info/entry_points.txt
formic.egg-info/top_level.txt
formic.egg-info/zip-safe