Metadata-Version: 1.0
Name: formic
Version: 0.9beta8
Summary: An implementation of Apache Ant FileSet and Globs
Home-page: http://www.aviser.asia/formic
Author: Aviser LLP, Singapore
Author-email: formic@aviser.asia
License: GPLv3+
Keywords: Apache Ant,glob,recurse,FileSet,file utilities,find
Platform: UNKNOWN
Classifier: License :: OSI Approved :: GNU General Public License v3 or later (GPLv3+)
Classifier: Programming Language :: Python
Classifier: Programming Language :: Python :: 2.7
Classifier: Development Status :: 4 - Beta
Classifier: Intended Audience :: Developers
Classifier: Topic :: Software Development :: Libraries
